libwmdrelax.cpython-37m-x86_64-linux-gnu.so
wmd/__init__.py
wmd-1.3.2.dist-info/WHEEL
wmd-1.3.2.dist-info/LICENSE.md
wmd-1.3.2.dist-info/top_level.txt
wmd-1.3.2.dist-info/METADATA
wmd-1.3.2.dist-info/RECORD
