Metadata-Version: 2.1
Name: wmd
Version: 1.3.2
Summary: Accelerated functions to calculate Word Mover's Distance
Home-page: https://github.com/src-d/wmd-relax
Author: source{d}
Author-email: vadim@sourced.tech
License: Apache Software License
Download-URL: https://github.com/src-d/wmd-relax
Platform: UNKNOWN
Classifier: Development Status :: 5 - Production/Stable
Classifier: Intended Audience :: Developers
Classifier: License :: OSI Approved :: Apache Software License
Classifier: Operating System :: POSIX :: Linux
Classifier: Topic :: Scientific/Engineering :: Information Analysis
Classifier: Programming Language :: Python :: 3.4
Classifier: Programming Language :: Python :: 3.5
Classifier: Programming Language :: Python :: 3.6
Requires-Dist: numpy
